{"results": [{"alternatives": [{"transcript": "they is delivering but", "confidence": 0.63372695}], "resultEndTime": "461.520s", "languageCode": "en-us"}, {"alternatives": [{"transcript": "I'm in onigiri", "confidence": 0.5474892}], "resultEndTime": "1139.260s", "languageCode": "en-us"}, {"alternatives": [{"transcript": "read my two ladies The Following song is one of the most beautiful piano pieces I ever played", "confidence": 0.90557015}], "resultEndTime": "1229.080s", "languageCode": "en-us"}, {"alternatives": [{"transcript": " the name of the composer Natalie Cole and Linda Williams the name of this song", "confidence": 0.9343542}], "resultEndTime": "1240.310s", "languageCode": "en-us"}, {"alternatives": [{"transcript": " Ethan gamer TV", "confidence": 0.45299658}], "resultEndTime": "1405.090s", "languageCode": "en-us"}], "totalBilledTime": "1889s", "requestId": "6553400631926098371"}