{"text": " © transcript Emily Beynon Thank you. Solo y disfruto, solo y desnudo viene a llorar Con verde horizonte, verde llorar Con silencios de verde desconsolar Con verde horizonte, verde llorar Con silencios de verde desconsolar Thank you very much. are living the wait Let the people Ultimately With green horizons With a green horizon to cry, with silences to see her disconcerted. El cantor andei son, patristenen, Sin ver que el Padre su grito enciende. THE END ¶¶ Thank you. ¶¶ © BF-WATCH TV 2021 Here I will return, reincarnation, cycle of life, the cradle of humanity, yes, Lord. The evolution of the earth and of the people, everything is pending of our love. La juventud merece algo mejor que la guerra y opresión y la contaminación Vamos a sembrar conciencia en este mundo con amor y devoción Para los niños, para los viejos, para nosotros y nuestro pueblo Aprenderá Mañana es para los niños Hay que pensar en mañana y en destino Mañana es para los niños Hay que pensar en mañana y el destino Mañana es para los niños Hay que pensar en saying is believing but ¶¶ We'll be right back. El amor, lo que el mundo necesita El amor, lo que el mundo necesita Cada día más el mundo requiere paz El amor, lo que el mundo necesita ¶¶ ¶¶ ¶¶ Comprehension y bondad esenciales para la humanidad. Cada día más, el mundo requiere pan. Amor para los viejos, que son los grandes de la vida. Cada día más, el mundo requiere pan. Amor y cariño para los niños hace un futuro mejor. Cada día más, el mundo requiere pan. We'll see you next time. Thank you. Thank you. Thank you. Thank you. Add 1 teaspoon of salt and 1 teaspoon of black pepper to the pan and stir-fry over medium-low heat for 10 minutes. Add 1 teaspoon of salt and 1 teaspoon of black pepper to the pan and stir-fry over medium-low heat for 10 minutes. Add 1 teaspoon of black pepper to the pan and stir-fry over medium-low heat for 10 minutes. Add 1 teaspoon of salt and 1 teaspoon of black pepper to the pan and stir-fry over medium-low heat for 10 minutes. Thank you. Thank you. Thank you. Thank you. Thank you. Thank you. Thank you. Thank you. Thank you. Thank you. Thank you. Thank you. ¶¶ ¶¶ Thank you. Thank you. ¶¶ ¶¶ Written by two ladies, the following song is one of the most beautiful piano pieces I ever played. The name of the composers are Natalie Cole and Linda Williams. The name of the song is La Costa. Thank you. Thank you. Thank you for watching. I will continue to the next. Thank you for watching. I will continue to the next. Thank you for watching. Thank you for watching. Thank you. Thank you for watching. I will continue to the next. I will continue to the next. I will continue to the next. I will continue to the next. I will continue to the next. Thank you for watching. I will continue to the next. I will continue to the next. I will continue to the next. I will continue to the next. I will continue to the next. Thank you. Thank you. We'll be right back. Thank you. Thank you. Thank you. Thank you. Thank you. Thank you. Thank you. ¶¶ piano plays softly Thank you. Thank you. Thank you. Thank you.", "segments": [{"id": 0, "seek": 0, "start": 0.0, "end": 29.98, "text": " © transcript Emily Beynon", "tokens": [50365, 1815, 102, 24444, 15034, 879, 2534, 266, 51864], "temperature": 0.0, "avg_logprob": -0.6121824741363525, "compression_ratio": 0.7647058823529411, "no_speech_prob": 0.8583585023880005}, {"id": 1, "seek": 3000, "start": 30.0, "end": 59.980000000000004, "text": " Thank you.", "tokens": [50365, 1044, 291, 13, 51864], "temperature": 0.0, "avg_logprob": -0.5886703729629517, "compression_ratio": 0.5555555555555556, "no_speech_prob": 0.37253400683403015}, {"id": 2, "seek": 6000, "start": 60.0, "end": 65.0, "text": " Solo y disfruto, solo y desnudo viene a llorar", "tokens": [50365, 26452, 288, 37114, 8262, 11, 6944, 288, 730, 77, 6207, 19561, 257, 4849, 42967, 50615], "temperature": 0.0, "avg_logprob": -0.27715994517008463, "compression_ratio": 2.021978021978022, "no_speech_prob": 0.7639226317405701}, {"id": 3, "seek": 6000, "start": 65.0, "end": 70.0, "text": " Con verde horizonte, verde llorar", "tokens": [50615, 2656, 29653, 7937, 10219, 11, 29653, 4849, 42967, 50865], "temperature": 0.0, "avg_logprob": -0.27715994517008463, "compression_ratio": 2.021978021978022, "no_speech_prob": 0.7639226317405701}, {"id": 4, "seek": 6000, "start": 70.0, "end": 75.0, "text": " Con silencios de verde desconsolar", "tokens": [50865, 2656, 3425, 268, 23132, 368, 29653, 7471, 892, 15276, 51115], "temperature": 0.0, "avg_logprob": -0.27715994517008463, "compression_ratio": 2.021978021978022, "no_speech_prob": 0.7639226317405701}, {"id": 5, "seek": 6000, "start": 75.0, "end": 80.0, "text": " Con verde horizonte, verde llorar", "tokens": [51115, 2656, 29653, 7937, 10219, 11, 29653, 4849, 42967, 51365], "temperature": 0.0, "avg_logprob": -0.27715994517008463, "compression_ratio": 2.021978021978022, "no_speech_prob": 0.7639226317405701}, {"id": 6, "seek": 6000, "start": 80.0, "end": 85.0, "text": " Con silencios de verde desconsolar", "tokens": [51365, 2656, 3425, 268, 23132, 368, 29653, 7471, 892, 15276, 51615], "temperature": 0.0, "avg_logprob": -0.27715994517008463, "compression_ratio": 2.021978021978022, "no_speech_prob": 0.7639226317405701}, {"id": 7, "seek": 8500, "start": 85.0, "end": 114.98, "text": " Thank you very much.", "tokens": [50365, 1044, 291, 588, 709, 13, 51864], "temperature": 0.0, "avg_logprob": -0.957692563533783, "compression_ratio": 0.7142857142857143, "no_speech_prob": 0.5222368240356445}, {"id": 8, "seek": 11500, "start": 115.0, "end": 118.34, "text": " are living the wait", "tokens": [50365, 366, 2647, 264, 1699, 50532], "temperature": 1.0, "avg_logprob": -3.5564117431640625, "compression_ratio": 0.9848484848484849, "no_speech_prob": 0.49658796191215515}, {"id": 9, "seek": 11500, "start": 119.06, "end": 133.44, "text": " Let the people Ultimately", "tokens": [50568, 961, 264, 561, 23921, 51287], "temperature": 1.0, "avg_logprob": -3.5564117431640625, "compression_ratio": 0.9848484848484849, "no_speech_prob": 0.49658796191215515}, {"id": 10, "seek": 11500, "start": 141.34, "end": 143.18, "text": " With green horizons", "tokens": [51682, 2022, 3092, 7937, 892, 51774], "temperature": 1.0, "avg_logprob": -3.5564117431640625, "compression_ratio": 0.9848484848484849, "no_speech_prob": 0.49658796191215515}, {"id": 11, "seek": 14318, "start": 143.18, "end": 163.18, "text": " With a green horizon to cry, with silences to see her disconcerted.", "tokens": [50365, 2022, 257, 3092, 18046, 281, 3305, 11, 365, 3425, 2667, 281, 536, 720, 717, 1671, 48999, 292, 13, 51365], "temperature": 0.0, "avg_logprob": -0.9752172123302113, "compression_ratio": 1.0151515151515151, "no_speech_prob": 0.710068941116333}, {"id": 12, "seek": 16318, "start": 163.18, "end": 168.14000000000001, "text": " El cantor andei son, patristenen,", "tokens": [50365, 2699, 11223, 284, 293, 17067, 1872, 11, 1947, 81, 4821, 268, 11, 50613], "temperature": 1.0, "avg_logprob": -1.1797311147054037, "compression_ratio": 1.0, "no_speech_prob": 0.184843510389328}, {"id": 13, "seek": 16318, "start": 168.14000000000001, "end": 188.46, "text": " Sin ver que el Padre su grito enciende.", "tokens": [50613, 11187, 1306, 631, 806, 18691, 265, 459, 677, 3528, 465, 537, 5445, 13, 51629], "temperature": 1.0, "avg_logprob": -1.1797311147054037, "compression_ratio": 1.0, "no_speech_prob": 0.184843510389328}, {"id": 14, "seek": 19318, "start": 193.18, "end": 223.16, "text": " THE END", "tokens": [50365, 5663, 462, 13360, 51864], "temperature": 0.0, "avg_logprob": -0.8117620150248209, "compression_ratio": 0.4666666666666667, "no_speech_prob": 0.9298567771911621}, {"id": 15, "seek": 22318, "start": 223.18, "end": 233.18, "text": " ¶¶", "tokens": [50365, 1815, 114, 126, 114, 50865], "temperature": 0.0, "avg_logprob": -0.5900054574012756, "compression_ratio": 0.3333333333333333, "no_speech_prob": 0.8773030042648315}, {"id": 16, "seek": 23318, "start": 233.18, "end": 263.16, "text": " Thank you.", "tokens": [50365, 1044, 291, 13, 51864], "temperature": 0.0, "avg_logprob": -0.5594846407572428, "compression_ratio": 0.5555555555555556, "no_speech_prob": 0.9078038930892944}, {"id": 17, "seek": 26318, "start": 263.18, "end": 292.18, "text": " ¶¶", "tokens": [50365, 1815, 114, 126, 114, 51815], "temperature": 0.0, "avg_logprob": -0.5371861457824707, "compression_ratio": 0.3333333333333333, "no_speech_prob": 0.9208040833473206}, {"id": 18, "seek": 29218, "start": 292.18, "end": 322.16, "text": " © BF-WATCH TV 2021", "tokens": [50365, 1815, 102, 363, 37, 12, 54, 2218, 5462, 3558, 7201, 51864], "temperature": 0.0, "avg_logprob": -0.42063573690561146, "compression_ratio": 0.7037037037037037, "no_speech_prob": 0.5200372338294983}, {"id": 19, "seek": 32218, "start": 322.18, "end": 332.92, "text": " Here I will return, reincarnation, cycle of life, the cradle of humanity, yes, Lord.", "tokens": [50365, 1692, 286, 486, 2736, 11, 48343, 399, 11, 6586, 295, 993, 11, 264, 48081, 295, 10243, 11, 2086, 11, 3257, 13, 50902], "temperature": 0.0, "avg_logprob": -0.45175894823941315, "compression_ratio": 1.32, "no_speech_prob": 0.938626766204834}, {"id": 20, "seek": 32218, "start": 333.78000000000003, "end": 342.56, "text": " The evolution of the earth and of the people, everything is pending of our love.", "tokens": [50945, 440, 9303, 295, 264, 4120, 293, 295, 264, 561, 11, 1203, 307, 32110, 295, 527, 959, 13, 51384], "temperature": 0.0, "avg_logprob": -0.45175894823941315, "compression_ratio": 1.32, "no_speech_prob": 0.938626766204834}, {"id": 21, "seek": 34256, "start": 342.56, "end": 351.56, "text": " La juventud merece algo mejor que la guerra y opresión y la contaminación", "tokens": [50365, 2369, 3649, 2475, 532, 8401, 384, 8655, 11479, 631, 635, 27542, 288, 999, 495, 2560, 288, 635, 27562, 3482, 50815], "temperature": 0.0, "avg_logprob": -0.20242226123809814, "compression_ratio": 1.3835616438356164, "no_speech_prob": 0.7216570973396301}, {"id": 22, "seek": 34256, "start": 351.56, "end": 358.56, "text": " Vamos a sembrar conciencia en este mundo con amor y devoción", "tokens": [50815, 10894, 257, 4361, 30280, 416, 537, 10974, 465, 4065, 7968, 416, 15543, 288, 49717, 5687, 51165], "temperature": 0.0, "avg_logprob": -0.20242226123809814, "compression_ratio": 1.3835616438356164, "no_speech_prob": 0.7216570973396301}, {"id": 23, "seek": 34256, "start": 359.18, "end": 367.14, "text": " Para los niños, para los viejos, para nosotros y nuestro pueblo", "tokens": [51196, 11107, 1750, 30712, 11, 1690, 1750, 4941, 19136, 11, 1690, 13863, 288, 14726, 33764, 51594], "temperature": 0.0, "avg_logprob": -0.20242226123809814, "compression_ratio": 1.3835616438356164, "no_speech_prob": 0.7216570973396301}, {"id": 24, "seek": 36714, "start": 367.14, "end": 371.32, "text": " Aprenderá", "tokens": [50365, 316, 3712, 20535, 842, 50574], "temperature": 0.0, "avg_logprob": -0.42697295436152705, "compression_ratio": 1.0, "no_speech_prob": 0.4490906596183777}, {"id": 25, "seek": 36714, "start": 371.32, "end": 380.34, "text": " Mañana es para los niños", "tokens": [50574, 4042, 31823, 785, 1690, 1750, 30712, 51025], "temperature": 0.0, "avg_logprob": -0.42697295436152705, "compression_ratio": 1.0, "no_speech_prob": 0.4490906596183777}, {"id": 26, "seek": 36714, "start": 380.34, "end": 384.91999999999996, "text": " Hay que pensar en mañana y en destino", "tokens": [51025, 8721, 631, 18321, 465, 33573, 288, 465, 2677, 2982, 51254], "temperature": 0.0, "avg_logprob": -0.42697295436152705, "compression_ratio": 1.0, "no_speech_prob": 0.4490906596183777}, {"id": 27, "seek": 38492, "start": 384.92, "end": 398.64000000000004, "text": " Mañana es para los niños", "tokens": [50365, 4042, 31823, 785, 1690, 1750, 30712, 51051], "temperature": 0.0, "avg_logprob": -0.31100752240135554, "compression_ratio": 0.9701492537313433, "no_speech_prob": 0.22347907721996307}, {"id": 28, "seek": 38492, "start": 398.64000000000004, "end": 403.12, "text": " Hay que pensar en mañana y el destino", "tokens": [51051, 8721, 631, 18321, 465, 33573, 288, 806, 2677, 2982, 51275], "temperature": 0.0, "avg_logprob": -0.31100752240135554, "compression_ratio": 0.9701492537313433, "no_speech_prob": 0.22347907721996307}, {"id": 29, "seek": 40312, "start": 403.12, "end": 416.7, "text": " Mañana es para los niños", "tokens": [50365, 4042, 31823, 785, 1690, 1750, 30712, 51044], "temperature": 0.0, "avg_logprob": -0.5646671930948893, "compression_ratio": 0.8627450980392157, "no_speech_prob": 0.49736306071281433}, {"id": 30, "seek": 40312, "start": 416.7, "end": 419.14, "text": " Hay que pensar en", "tokens": [51044, 8721, 631, 18321, 465, 51166], "temperature": 0.0, "avg_logprob": -0.5646671930948893, "compression_ratio": 0.8627450980392157, "no_speech_prob": 0.49736306071281433}, {"id": 31, "seek": 43312, "start": 433.12, "end": 459.96, "text": " saying is believing but", "tokens": [50365, 1566, 307, 16594, 457, 51707], "temperature": 0.0, "avg_logprob": -0.6441349302019391, "compression_ratio": 0.8214285714285714, "no_speech_prob": 0.6223486065864563}, {"id": 32, "seek": 46312, "start": 463.12, "end": 473.12, "text": " ¶¶", "tokens": [50365, 1815, 114, 126, 114, 50865], "temperature": 0.0, "avg_logprob": -0.6125149130821228, "compression_ratio": 0.3333333333333333, "no_speech_prob": 0.7054102420806885}, {"id": 33, "seek": 47312, "start": 473.12, "end": 503.1, "text": " We'll be right back.", "tokens": [50365, 492, 603, 312, 558, 646, 13, 51864], "temperature": 0.0, "avg_logprob": -0.5065842734442817, "compression_ratio": 0.7142857142857143, "no_speech_prob": 0.7852051854133606}, {"id": 34, "seek": 50312, "start": 503.12, "end": 515.12, "text": " El amor, lo que el mundo necesita El amor, lo que el mundo necesita", "tokens": [50365, 2699, 15543, 11, 450, 631, 806, 7968, 45485, 2699, 15543, 11, 450, 631, 806, 7968, 45485, 50965], "temperature": 0.0, "avg_logprob": -0.40403895629079717, "compression_ratio": 1.8157894736842106, "no_speech_prob": 0.9005613327026367}, {"id": 35, "seek": 50312, "start": 515.12, "end": 524.12, "text": " Cada día más el mundo requiere paz El amor, lo que el mundo necesita", "tokens": [50965, 38603, 12271, 3573, 806, 7968, 1724, 14412, 30032, 2699, 15543, 11, 450, 631, 806, 7968, 45485, 51415], "temperature": 0.0, "avg_logprob": -0.40403895629079717, "compression_ratio": 1.8157894736842106, "no_speech_prob": 0.9005613327026367}, {"id": 36, "seek": 52412, "start": 524.12, "end": 534.12, "text": " ¶¶", "tokens": [50365, 1815, 114, 126, 114, 50865], "temperature": 0.0, "avg_logprob": -0.5211873054504395, "compression_ratio": 0.875, "no_speech_prob": 0.9109185338020325}, {"id": 37, "seek": 52412, "start": 534.12, "end": 544.12, "text": " ¶¶", "tokens": [50865, 1815, 114, 126, 114, 51365], "temperature": 0.0, "avg_logprob": -0.5211873054504395, "compression_ratio": 0.875, "no_speech_prob": 0.9109185338020325}, {"id": 38, "seek": 52412, "start": 544.12, "end": 550.12, "text": " ¶¶", "tokens": [51365, 1815, 114, 126, 114, 51665], "temperature": 0.0, "avg_logprob": -0.5211873054504395, "compression_ratio": 0.875, "no_speech_prob": 0.9109185338020325}, {"id": 39, "seek": 55012, "start": 550.12, "end": 554.12, "text": " Comprehension y bondad esenciales para la humanidad.", "tokens": [50365, 2432, 40128, 3378, 288, 6086, 345, 785, 26567, 279, 1690, 635, 1952, 4580, 13, 50565], "temperature": 0.0, "avg_logprob": -0.20623634601461477, "compression_ratio": 1.8523489932885906, "no_speech_prob": 0.9421161413192749}, {"id": 40, "seek": 55012, "start": 554.12, "end": 558.12, "text": " Cada día más, el mundo requiere pan.", "tokens": [50565, 38603, 12271, 3573, 11, 806, 7968, 1724, 14412, 2462, 13, 50765], "temperature": 0.0, "avg_logprob": -0.20623634601461477, "compression_ratio": 1.8523489932885906, "no_speech_prob": 0.9421161413192749}, {"id": 41, "seek": 55012, "start": 558.12, "end": 563.12, "text": " Amor para los viejos, que son los grandes de la vida.", "tokens": [50765, 2012, 284, 1690, 1750, 4941, 19136, 11, 631, 1872, 1750, 16640, 368, 635, 7644, 13, 51015], "temperature": 0.0, "avg_logprob": -0.20623634601461477, "compression_ratio": 1.8523489932885906, "no_speech_prob": 0.9421161413192749}, {"id": 42, "seek": 55012, "start": 563.12, "end": 567.12, "text": " Cada día más, el mundo requiere pan.", "tokens": [51015, 38603, 12271, 3573, 11, 806, 7968, 1724, 14412, 2462, 13, 51215], "temperature": 0.0, "avg_logprob": -0.20623634601461477, "compression_ratio": 1.8523489932885906, "no_speech_prob": 0.9421161413192749}, {"id": 43, "seek": 55012, "start": 567.12, "end": 572.12, "text": " Amor y cariño para los niños hace un futuro mejor.", "tokens": [51215, 2012, 284, 288, 1032, 72, 7716, 1690, 1750, 30712, 10032, 517, 23953, 11479, 13, 51465], "temperature": 0.0, "avg_logprob": -0.20623634601461477, "compression_ratio": 1.8523489932885906, "no_speech_prob": 0.9421161413192749}, {"id": 44, "seek": 55012, "start": 572.12, "end": 575.12, "text": " Cada día más, el mundo requiere pan.", "tokens": [51465, 38603, 12271, 3573, 11, 806, 7968, 1724, 14412, 2462, 13, 51615], "temperature": 0.0, "avg_logprob": -0.20623634601461477, "compression_ratio": 1.8523489932885906, "no_speech_prob": 0.9421161413192749}, {"id": 45, "seek": 57512, "start": 575.12, "end": 605.1, "text": " We'll see you next time.", "tokens": [50365, 492, 603, 536, 291, 958, 565, 13, 51864], "temperature": 0.0, "avg_logprob": -0.7240039825439453, "compression_ratio": 0.75, "no_speech_prob": 0.8758386373519897}, {"id": 46, "seek": 60512, "start": 605.12, "end": 635.1, "text": " Thank you.", "tokens": [50365, 1044, 291, 13, 51864], "temperature": 0.0, "avg_logprob": -0.6102254390716553, "compression_ratio": 0.5555555555555556, "no_speech_prob": 0.8454552888870239}, {"id": 47, "seek": 63512, "start": 635.12, "end": 665.1, "text": " Thank you.", "tokens": [50365, 1044, 291, 13, 51864], "temperature": 0.0, "avg_logprob": -0.6254707177480062, "compression_ratio": 0.5555555555555556, "no_speech_prob": 0.803125262260437}, {"id": 48, "seek": 66512, "start": 665.12, "end": 695.1, "text": " Thank you.", "tokens": [50365, 1044, 291, 13, 51864], "temperature": 0.0, "avg_logprob": -0.5238522291183472, "compression_ratio": 0.5555555555555556, "no_speech_prob": 0.7357046008110046}, {"id": 49, "seek": 69512, "start": 695.12, "end": 725.1, "text": " Thank you.", "tokens": [50365, 1044, 291, 13, 51864], "temperature": 0.0, "avg_logprob": -0.5493545929590861, "compression_ratio": 0.5555555555555556, "no_speech_prob": 0.8268238306045532}, {"id": 50, "seek": 72512, "start": 725.12, "end": 732.12, "text": " Add 1 teaspoon of salt and 1 teaspoon of black pepper to the pan and stir-fry over medium-low heat for 10 minutes.", "tokens": [50365, 5349, 502, 17237, 295, 5139, 293, 502, 17237, 295, 2211, 8532, 281, 264, 2462, 293, 8946, 12, 35299, 670, 6399, 12, 14107, 3738, 337, 1266, 2077, 13, 50715], "temperature": 0.0, "avg_logprob": -0.5293167586875173, "compression_ratio": 4.316831683168317, "no_speech_prob": 0.6040186285972595}, {"id": 51, "seek": 72512, "start": 732.12, "end": 737.12, "text": " Add 1 teaspoon of salt and 1 teaspoon of black pepper to the pan and stir-fry over medium-low heat for 10 minutes.", "tokens": [50715, 5349, 502, 17237, 295, 5139, 293, 502, 17237, 295, 2211, 8532, 281, 264, 2462, 293, 8946, 12, 35299, 670, 6399, 12, 14107, 3738, 337, 1266, 2077, 13, 50965], "temperature": 0.0, "avg_logprob": -0.5293167586875173, "compression_ratio": 4.316831683168317, "no_speech_prob": 0.6040186285972595}, {"id": 52, "seek": 72512, "start": 737.12, "end": 743.12, "text": " Add 1 teaspoon of black pepper to the pan and stir-fry over medium-low heat for 10 minutes.", "tokens": [50965, 5349, 502, 17237, 295, 2211, 8532, 281, 264, 2462, 293, 8946, 12, 35299, 670, 6399, 12, 14107, 3738, 337, 1266, 2077, 13, 51265], "temperature": 0.0, "avg_logprob": -0.5293167586875173, "compression_ratio": 4.316831683168317, "no_speech_prob": 0.6040186285972595}, {"id": 53, "seek": 72512, "start": 743.12, "end": 750.12, "text": " Add 1 teaspoon of salt and 1 teaspoon of black pepper to the pan and stir-fry over medium-low heat for 10 minutes.", "tokens": [51265, 5349, 502, 17237, 295, 5139, 293, 502, 17237, 295, 2211, 8532, 281, 264, 2462, 293, 8946, 12, 35299, 670, 6399, 12, 14107, 3738, 337, 1266, 2077, 13, 51615], "temperature": 0.0, "avg_logprob": -0.5293167586875173, "compression_ratio": 4.316831683168317, "no_speech_prob": 0.6040186285972595}, {"id": 54, "seek": 75012, "start": 750.12, "end": 780.1, "text": " Thank you.", "tokens": [50365, 1044, 291, 13, 51864], "temperature": 0.0, "avg_logprob": -0.4571220874786377, "compression_ratio": 0.5555555555555556, "no_speech_prob": 0.7870112657546997}, {"id": 55, "seek": 78012, "start": 780.12, "end": 810.1, "text": " Thank you.", "tokens": [50365, 1044, 291, 13, 51864], "temperature": 0.0, "avg_logprob": -0.5592310428619385, "compression_ratio": 0.5555555555555556, "no_speech_prob": 0.5454503893852234}, {"id": 56, "seek": 81012, "start": 810.12, "end": 840.1, "text": " Thank you.", "tokens": [50365, 1044, 291, 13, 51864], "temperature": 0.0, "avg_logprob": -0.43079670270284015, "compression_ratio": 0.5555555555555556, "no_speech_prob": 0.8274779915809631}, {"id": 57, "seek": 84012, "start": 840.12, "end": 870.1, "text": " Thank you.", "tokens": [50365, 1044, 291, 13, 51864], "temperature": 0.0, "avg_logprob": -0.4351566632588704, "compression_ratio": 0.5555555555555556, "no_speech_prob": 0.8081883788108826}, {"id": 58, "seek": 87012, "start": 870.12, "end": 900.1, "text": " Thank you.", "tokens": [50365, 1044, 291, 13, 51864], "temperature": 0.0, "avg_logprob": -0.3656041622161865, "compression_ratio": 0.5555555555555556, "no_speech_prob": 0.7730330228805542}, {"id": 59, "seek": 90012, "start": 900.12, "end": 930.1, "text": " Thank you.", "tokens": [50365, 1044, 291, 13, 51864], "temperature": 0.0, "avg_logprob": -0.6572858492533366, "compression_ratio": 0.5555555555555556, "no_speech_prob": 0.9216602444648743}, {"id": 60, "seek": 93012, "start": 930.12, "end": 960.1, "text": " Thank you.", "tokens": [50365, 1044, 291, 13, 51864], "temperature": 0.0, "avg_logprob": -0.29313339789708454, "compression_ratio": 0.5555555555555556, "no_speech_prob": 0.8482860922813416}, {"id": 61, "seek": 96012, "start": 960.12, "end": 990.1, "text": " Thank you.", "tokens": [50365, 1044, 291, 13, 51864], "temperature": 0.0, "avg_logprob": -0.6871849695841471, "compression_ratio": 0.5555555555555556, "no_speech_prob": 0.8258586525917053}, {"id": 62, "seek": 99012, "start": 990.12, "end": 1020.1, "text": " Thank you.", "tokens": [50365, 1044, 291, 13, 51864], "temperature": 0.0, "avg_logprob": -0.26827549934387207, "compression_ratio": 0.5555555555555556, "no_speech_prob": 0.8111797571182251}, {"id": 63, "seek": 102012, "start": 1020.12, "end": 1050.1, "text": " Thank you.", "tokens": [50365, 1044, 291, 13, 51864], "temperature": 0.0, "avg_logprob": -0.28028533856074017, "compression_ratio": 0.5555555555555556, "no_speech_prob": 0.83868008852005}, {"id": 64, "seek": 105012, "start": 1050.12, "end": 1080.1, "text": " Thank you.", "tokens": [50365, 1044, 291, 13, 51864], "temperature": 0.0, "avg_logprob": -0.3164529005686442, "compression_ratio": 0.5555555555555556, "no_speech_prob": 0.8680925965309143}, {"id": 65, "seek": 108012, "start": 1080.12, "end": 1110.1, "text": " Thank you.", "tokens": [50365, 1044, 291, 13, 51864], "temperature": 0.0, "avg_logprob": -0.2716513474782308, "compression_ratio": 0.5555555555555556, "no_speech_prob": 0.8352003693580627}, {"id": 66, "seek": 111012, "start": 1110.12, "end": 1135.12, "text": " ¶¶", "tokens": [50365, 1815, 114, 126, 114, 51615], "temperature": 0.0, "avg_logprob": -0.7404854847834661, "compression_ratio": 0.5625, "no_speech_prob": 0.5485285520553589}, {"id": 67, "seek": 111012, "start": 1135.12, "end": 1139.12, "text": " ¶¶", "tokens": [51615, 1815, 114, 126, 114, 51815], "temperature": 0.0, "avg_logprob": -0.7404854847834661, "compression_ratio": 0.5625, "no_speech_prob": 0.5485285520553589}, {"id": 68, "seek": 114012, "start": 1140.12, "end": 1170.1, "text": " Thank you.", "tokens": [50365, 1044, 291, 13, 51864], "temperature": 0.0, "avg_logprob": -0.4692614475886027, "compression_ratio": 0.5555555555555556, "no_speech_prob": 0.6942216157913208}, {"id": 69, "seek": 117012, "start": 1170.12, "end": 1200.1, "text": " Thank you.", "tokens": [50365, 1044, 291, 13, 51864], "temperature": 0.0, "avg_logprob": -0.4552982250849406, "compression_ratio": 0.5555555555555556, "no_speech_prob": 0.8157798051834106}, {"id": 70, "seek": 120012, "start": 1200.12, "end": 1210.12, "text": " ¶¶", "tokens": [50365, 1815, 114, 126, 114, 50865], "temperature": 0.0, "avg_logprob": -0.41039422842172474, "compression_ratio": 1.1134020618556701, "no_speech_prob": 0.5055886507034302}, {"id": 71, "seek": 120012, "start": 1210.12, "end": 1220.12, "text": " ¶¶", "tokens": [50865, 1815, 114, 126, 114, 51365], "temperature": 0.0, "avg_logprob": -0.41039422842172474, "compression_ratio": 1.1134020618556701, "no_speech_prob": 0.5055886507034302}, {"id": 72, "seek": 120012, "start": 1220.12, "end": 1222.12, "text": " Written by two ladies,", "tokens": [51365, 10159, 2987, 538, 732, 9974, 11, 51465], "temperature": 0.0, "avg_logprob": -0.41039422842172474, "compression_ratio": 1.1134020618556701, "no_speech_prob": 0.5055886507034302}, {"id": 73, "seek": 120012, "start": 1222.12, "end": 1229.12, "text": " the following song is one of the most beautiful piano pieces I ever played.", "tokens": [51465, 264, 3480, 2153, 307, 472, 295, 264, 881, 2238, 9211, 3755, 286, 1562, 3737, 13, 51815], "temperature": 0.0, "avg_logprob": -0.41039422842172474, "compression_ratio": 1.1134020618556701, "no_speech_prob": 0.5055886507034302}, {"id": 74, "seek": 122912, "start": 1229.12, "end": 1235.7399999999998, "text": " The name of the composers are Natalie Cole and Linda Williams.", "tokens": [50365, 440, 1315, 295, 264, 43872, 366, 29574, 20394, 293, 20324, 12929, 13, 50696], "temperature": 0.0, "avg_logprob": -0.23075672296377328, "compression_ratio": 1.1851851851851851, "no_speech_prob": 0.4386342465877533}, {"id": 75, "seek": 122912, "start": 1236.62, "end": 1239.54, "text": " The name of the song is La Costa.", "tokens": [50740, 440, 1315, 295, 264, 2153, 307, 2369, 28440, 13, 50886], "temperature": 0.0, "avg_logprob": -0.23075672296377328, "compression_ratio": 1.1851851851851851, "no_speech_prob": 0.4386342465877533}, {"id": 76, "seek": 125912, "start": 1259.12, "end": 1289.1, "text": " Thank you.", "tokens": [50365, 1044, 291, 13, 51864], "temperature": 0.0, "avg_logprob": -0.3679775396982829, "compression_ratio": 0.5555555555555556, "no_speech_prob": 0.9290491938591003}, {"id": 77, "seek": 128912, "start": 1289.12, "end": 1319.1, "text": " Thank you.", "tokens": [50365, 1044, 291, 13, 51864], "temperature": 0.0, "avg_logprob": -0.439644455909729, "compression_ratio": 0.5555555555555556, "no_speech_prob": 0.8738833069801331}, {"id": 78, "seek": 131912, "start": 1319.12, "end": 1324.1, "text": " Thank you for watching.", "tokens": [50365, 1044, 291, 337, 1976, 13, 50614], "temperature": 0.0, "avg_logprob": -0.40937379995981854, "compression_ratio": 2.3181818181818183, "no_speech_prob": 0.7679905295372009}, {"id": 79, "seek": 131912, "start": 1324.1, "end": 1329.08, "text": " I will continue to the next.", "tokens": [50614, 286, 486, 2354, 281, 264, 958, 13, 50863], "temperature": 0.0, "avg_logprob": -0.40937379995981854, "compression_ratio": 2.3181818181818183, "no_speech_prob": 0.7679905295372009}, {"id": 80, "seek": 131912, "start": 1329.08, "end": 1334.06, "text": " Thank you for watching.", "tokens": [50863, 1044, 291, 337, 1976, 13, 51112], "temperature": 0.0, "avg_logprob": -0.40937379995981854, "compression_ratio": 2.3181818181818183, "no_speech_prob": 0.7679905295372009}, {"id": 81, "seek": 131912, "start": 1334.06, "end": 1339.04, "text": " I will continue to the next.", "tokens": [51112, 286, 486, 2354, 281, 264, 958, 13, 51361], "temperature": 0.0, "avg_logprob": -0.40937379995981854, "compression_ratio": 2.3181818181818183, "no_speech_prob": 0.7679905295372009}, {"id": 82, "seek": 131912, "start": 1339.04, "end": 1344.02, "text": " Thank you for watching.", "tokens": [51361, 1044, 291, 337, 1976, 13, 51610], "temperature": 0.0, "avg_logprob": -0.40937379995981854, "compression_ratio": 2.3181818181818183, "no_speech_prob": 0.7679905295372009}, {"id": 83, "seek": 131912, "start": 1344.02, "end": 1349.0, "text": " Thank you for watching.", "tokens": [51610, 1044, 291, 337, 1976, 13, 51859], "temperature": 0.0, "avg_logprob": -0.40937379995981854, "compression_ratio": 2.3181818181818183, "no_speech_prob": 0.7679905295372009}, {"id": 84, "seek": 134900, "start": 1349.0, "end": 1378.98, "text": " Thank you.", "tokens": [50365, 1044, 291, 13, 51864], "temperature": 0.0, "avg_logprob": -0.4033439556757609, "compression_ratio": 0.5555555555555556, "no_speech_prob": 0.8568395376205444}, {"id": 85, "seek": 137900, "start": 1379.0, "end": 1383.98, "text": " Thank you for watching.", "tokens": [50365, 1044, 291, 337, 1976, 13, 50614], "temperature": 0.0, "avg_logprob": -0.362362543741862, "compression_ratio": 2.7540983606557377, "no_speech_prob": 0.7663360834121704}, {"id": 86, "seek": 137900, "start": 1383.98, "end": 1388.96, "text": " I will continue to the next.", "tokens": [50614, 286, 486, 2354, 281, 264, 958, 13, 50863], "temperature": 0.0, "avg_logprob": -0.362362543741862, "compression_ratio": 2.7540983606557377, "no_speech_prob": 0.7663360834121704}, {"id": 87, "seek": 137900, "start": 1388.96, "end": 1393.94, "text": " I will continue to the next.", "tokens": [50863, 286, 486, 2354, 281, 264, 958, 13, 51112], "temperature": 0.0, "avg_logprob": -0.362362543741862, "compression_ratio": 2.7540983606557377, "no_speech_prob": 0.7663360834121704}, {"id": 88, "seek": 137900, "start": 1393.94, "end": 1398.92, "text": " I will continue to the next.", "tokens": [51112, 286, 486, 2354, 281, 264, 958, 13, 51361], "temperature": 0.0, "avg_logprob": -0.362362543741862, "compression_ratio": 2.7540983606557377, "no_speech_prob": 0.7663360834121704}, {"id": 89, "seek": 137900, "start": 1398.92, "end": 1403.9, "text": " I will continue to the next.", "tokens": [51361, 286, 486, 2354, 281, 264, 958, 13, 51610], "temperature": 0.0, "avg_logprob": -0.362362543741862, "compression_ratio": 2.7540983606557377, "no_speech_prob": 0.7663360834121704}, {"id": 90, "seek": 137900, "start": 1403.9, "end": 1408.88, "text": " I will continue to the next.", "tokens": [51610, 286, 486, 2354, 281, 264, 958, 13, 51859], "temperature": 0.0, "avg_logprob": -0.362362543741862, "compression_ratio": 2.7540983606557377, "no_speech_prob": 0.7663360834121704}, {"id": 91, "seek": 140888, "start": 1408.88, "end": 1413.8600000000001, "text": " Thank you for watching.", "tokens": [50365, 1044, 291, 337, 1976, 13, 50614], "temperature": 0.0, "avg_logprob": -0.3517155823884187, "compression_ratio": 2.7540983606557377, "no_speech_prob": 0.7074404954910278}, {"id": 92, "seek": 140888, "start": 1413.8600000000001, "end": 1418.8400000000001, "text": " I will continue to the next.", "tokens": [50614, 286, 486, 2354, 281, 264, 958, 13, 50863], "temperature": 0.0, "avg_logprob": -0.3517155823884187, "compression_ratio": 2.7540983606557377, "no_speech_prob": 0.7074404954910278}, {"id": 93, "seek": 140888, "start": 1418.8400000000001, "end": 1423.8200000000002, "text": " I will continue to the next.", "tokens": [50863, 286, 486, 2354, 281, 264, 958, 13, 51112], "temperature": 0.0, "avg_logprob": -0.3517155823884187, "compression_ratio": 2.7540983606557377, "no_speech_prob": 0.7074404954910278}, {"id": 94, "seek": 140888, "start": 1423.8200000000002, "end": 1428.8000000000002, "text": " I will continue to the next.", "tokens": [51112, 286, 486, 2354, 281, 264, 958, 13, 51361], "temperature": 0.0, "avg_logprob": -0.3517155823884187, "compression_ratio": 2.7540983606557377, "no_speech_prob": 0.7074404954910278}, {"id": 95, "seek": 140888, "start": 1428.8000000000002, "end": 1433.7800000000002, "text": " I will continue to the next.", "tokens": [51361, 286, 486, 2354, 281, 264, 958, 13, 51610], "temperature": 0.0, "avg_logprob": -0.3517155823884187, "compression_ratio": 2.7540983606557377, "no_speech_prob": 0.7074404954910278}, {"id": 96, "seek": 140888, "start": 1433.7800000000002, "end": 1438.7600000000002, "text": " I will continue to the next.", "tokens": [51610, 286, 486, 2354, 281, 264, 958, 13, 51859], "temperature": 0.0, "avg_logprob": -0.3517155823884187, "compression_ratio": 2.7540983606557377, "no_speech_prob": 0.7074404954910278}, {"id": 97, "seek": 143876, "start": 1438.76, "end": 1468.74, "text": " Thank you.", "tokens": [50365, 1044, 291, 13, 51864], "temperature": 0.0, "avg_logprob": -0.413552204767863, "compression_ratio": 0.5555555555555556, "no_speech_prob": 0.8669475317001343}, {"id": 98, "seek": 146876, "start": 1468.76, "end": 1498.74, "text": " Thank you.", "tokens": [50365, 1044, 291, 13, 51864], "temperature": 0.0, "avg_logprob": -0.3629499673843384, "compression_ratio": 0.5555555555555556, "no_speech_prob": 0.7648605704307556}, {"id": 99, "seek": 149876, "start": 1498.76, "end": 1528.74, "text": " We'll be right back.", "tokens": [50365, 492, 603, 312, 558, 646, 13, 51864], "temperature": 0.0, "avg_logprob": -0.4395105044047038, "compression_ratio": 0.7142857142857143, "no_speech_prob": 0.8835095763206482}, {"id": 100, "seek": 152876, "start": 1528.76, "end": 1558.74, "text": " Thank you.", "tokens": [50365, 1044, 291, 13, 51864], "temperature": 0.0, "avg_logprob": -0.5030593872070312, "compression_ratio": 0.5555555555555556, "no_speech_prob": 0.9160422086715698}, {"id": 101, "seek": 155876, "start": 1558.76, "end": 1588.74, "text": " Thank you.", "tokens": [50365, 1044, 291, 13, 51864], "temperature": 0.0, "avg_logprob": -0.4876058101654053, "compression_ratio": 0.5555555555555556, "no_speech_prob": 0.9457884430885315}, {"id": 102, "seek": 158876, "start": 1588.76, "end": 1618.74, "text": " Thank you.", "tokens": [50365, 1044, 291, 13, 51864], "temperature": 0.0, "avg_logprob": -0.4177132447560628, "compression_ratio": 0.5555555555555556, "no_speech_prob": 0.8375303745269775}, {"id": 103, "seek": 161876, "start": 1618.76, "end": 1648.74, "text": " Thank you.", "tokens": [50365, 1044, 291, 13, 51864], "temperature": 0.0, "avg_logprob": -0.49260632197062176, "compression_ratio": 0.5555555555555556, "no_speech_prob": 0.9183558821678162}, {"id": 104, "seek": 164876, "start": 1648.76, "end": 1678.74, "text": " Thank you.", "tokens": [50365, 1044, 291, 13, 51864], "temperature": 0.0, "avg_logprob": -0.3894666830698649, "compression_ratio": 0.5555555555555556, "no_speech_prob": 0.9036800265312195}, {"id": 105, "seek": 167876, "start": 1678.76, "end": 1708.74, "text": " Thank you.", "tokens": [50365, 1044, 291, 13, 51864], "temperature": 0.0, "avg_logprob": -0.4310349225997925, "compression_ratio": 0.5555555555555556, "no_speech_prob": 0.9004954695701599}, {"id": 106, "seek": 170876, "start": 1708.76, "end": 1738.74, "text": " Thank you.", "tokens": [50365, 1044, 291, 13, 51864], "temperature": 0.0, "avg_logprob": -0.37186646461486816, "compression_ratio": 0.5555555555555556, "no_speech_prob": 0.820791482925415}, {"id": 107, "seek": 173876, "start": 1738.76, "end": 1748.76, "text": " ¶¶", "tokens": [50365, 1815, 114, 126, 114, 50865], "temperature": 0.0, "avg_logprob": -0.6090725064277649, "compression_ratio": 0.3333333333333333, "no_speech_prob": 0.9295023083686829}, {"id": 108, "seek": 174876, "start": 1748.76, "end": 1778.74, "text": " piano plays softly", "tokens": [50365, 9211, 5749, 30832, 51864], "temperature": 0.0, "avg_logprob": -0.6331806580225626, "compression_ratio": 0.6923076923076923, "no_speech_prob": 0.9210111498832703}, {"id": 109, "seek": 177876, "start": 1778.76, "end": 1808.74, "text": " Thank you.", "tokens": [50365, 1044, 291, 13, 51864], "temperature": 0.0, "avg_logprob": -0.4796911080678304, "compression_ratio": 0.5555555555555556, "no_speech_prob": 0.7271472215652466}, {"id": 110, "seek": 180876, "start": 1808.76, "end": 1838.74, "text": " Thank you.", "tokens": [50365, 1044, 291, 13, 51864], "temperature": 0.0, "avg_logprob": -0.3564456303914388, "compression_ratio": 0.5555555555555556, "no_speech_prob": 0.9349683523178101}, {"id": 111, "seek": 183876, "start": 1838.76, "end": 1868.74, "text": " Thank you.", "tokens": [50365, 1044, 291, 13, 51864], "temperature": 0.0, "avg_logprob": -0.4477411111195882, "compression_ratio": 0.5555555555555556, "no_speech_prob": 0.8854422569274902}, {"id": 112, "seek": 186876, "start": 1868.76, "end": 1896.8799999999999, "text": " Thank you.", "tokens": [50365, 1044, 291, 13, 51771], "temperature": 0.0, "avg_logprob": -0.544172445933024, "compression_ratio": 0.5555555555555556, "no_speech_prob": 0.179939404129982}], "language": "en"}